geomdl/cli/__init__.py
geomdl/cli/command_line.py
geomdl/cli/commands.py
geomdl/cli/utilities.py
geomdl.cli-0.5.4.dist-info/LICENSE
geomdl.cli-0.5.4.dist-info/METADATA
geomdl.cli-0.5.4.dist-info/WHEEL
geomdl.cli-0.5.4.dist-info/entry_points.txt
geomdl.cli-0.5.4.dist-info/top_level.txt
geomdl.cli-0.5.4.dist-info/RECORD
