Metadata-Version: 2.1
Name: geomdl.cli
Version: 0.5.4
Summary: Run geomdl from the command line
Home-page: https://github.com/orbingol/geomdl-cli
Author: Onur Rauf Bingol
Author-email: nurbs-python@googlegroups.com
License: MIT
Project-URL: Documentation, http://geomdl-cli.readthedocs.io/
Project-URL: Source, https://github.com/orbingol/geomdl-cli
Project-URL: Tracker, https://github.com/orbingol/geomdl-cli/issues
Keywords: NURBS B-Spline curve surface CAD modeling visualization surface-generator
Platform: UNKNOWN
Classifier: Development Status :: 4 - Beta
Classifier: Intended Audience :: Science/Research
Classifier: License :: OSI Approved :: MIT License
Classifier: Topic :: Scientific/Engineering :: Mathematics
Classifier: Topic :: Scientific/Engineering :: Visualization
Classifier: Operating System :: OS Independent
Classifier: Environment :: Console
Classifier: Programming Language :: Python :: 3
Classifier: Programming Language :: Python :: 3.4
Classifier: Programming Language :: Python :: 3.5
Classifier: Programming Language :: Python :: 3.6
Classifier: Programming Language :: Python :: 3.7
Requires-Dist: geomdl (>=5.0.0)
Requires-Dist: matplotlib
Requires-Dist: Jinja2 (>=2.10)
Requires-Dist: ruamel.yaml (>=0.15)
Requires-Dist: libconf
